distributions/Binomialdistribution.py
distributions/Gaussiandistribution.py
distributions/Generaldistribution.py
distributions/__init__.py
such_distribution-2.0.dist-info/METADATA
such_distribution-2.0.dist-info/WHEEL
such_distribution-2.0.dist-info/top_level.txt
such_distribution-2.0.dist-info/RECORD
