Metadata-Version: 2.1
Name: such-distribution
Version: 2.0
Summary: statistical distributions
Home-page: UNKNOWN
Author: UNKNOWN
Author-email: UNKNOWN
License: UNKNOWN
Platform: UNKNOWN
